django_cachekiller/__init__.py
django_cachekiller/templatetags/__init__.py
django_cachekiller/templatetags/cdnstaticfiles.py
django_cachekiller-0.6.dist-info/LICENSE
django_cachekiller-0.6.dist-info/METADATA
django_cachekiller-0.6.dist-info/WHEEL
django_cachekiller-0.6.dist-info/top_level.txt
django_cachekiller-0.6.dist-info/RECORD
