Metadata-Version: 2.1
Name: django-cachekiller
Version: 0.6
Summary: Static file CDN cache buster for fast site updates.
Home-page: https://github.com/meeb/django-cachekiller
Author: https://github.com/meeb
Author-email: meeb@meeb.org
License: MIT
Keywords: django,cache,buster,cdn,cachebuster
Platform: UNKNOWN
Classifier: Development Status :: 5 - Production/Stable
Classifier: Environment :: Web Environment
Classifier: Intended Audience :: Developers
Classifier: License :: OSI Approved :: MIT License
Classifier: Operating System :: OS Independent
Classifier: Programming Language :: Python
Classifier: Programming Language :: Python :: 3
Classifier: Topic :: Internet :: WWW/HTTP
Classifier: Topic :: Internet :: WWW/HTTP :: Dynamic Content
Classifier: Topic :: Software Development :: Libraries :: Application Frameworks
Classifier: Topic :: Software Development :: Libraries :: Python Modules
Requires-Dist: django
